{
  "welcome": "Добро пожаловать",
  "Login to your account": "Войдите в свой аккаунт",
  "Email": "Электронная почта",
  "Password": "Пароль",
  "Forgot password?": "Забыли пароль?",
  "Login": "Войти",
  "Sign Up": "Зарегистрироваться",
  "Don't have an account?": "Нет аккаунта?",
  "Login successful": "Вход выполнен успешно!",
  "Wrong email. This email is not registered.": "Неправильный адрес электронной почты. Он не зарегистрирован.",
  "Wrong email or Password. Please try again.": "Неверный email или пароль. Пожалуйста, попробуйте снова.",
  "An error occurred during login. Please try again.:": "Произошла ошибка при входе. Пожалуйста, попробуйте снова.",

  "Register": "Регистрация",
  "Create your account": "Создайте свой аккаунт",
  "Username": "Имя пользователя",
  "Confirm Password": "Подтвердите пароль",
  "Already have an account?": "Уже есть аккаунт?",
  "Sign In": "Войти",
  "You can now register!": "Теперь вы можете зарегистрироваться!",
  "Registration successful!": "Регистрация прошла успешно!",

  "auth/email-already-in-use": "Эта электронная почта уже используется.",
  "auth/invalid-email": "Неверный адрес электронной почты.",
  "auth/weak-password": "Пароль должен содержать не менее 6 символов.",
  "registration/generic-error": "Произошла ошибка при регистрации. Пожалуйста, попробуйте позже.",

  "validation.username-required": "Имя пользователя обязательно.",
  "validation.invalid-email": "Неверный адрес электронной почты.",
  "validation.email-required": "Электронная почта обязательна.",
  "validation.password-too-short": "Пароль должен быть не менее 6 символов.",
  "validation.password-required": "Пароль обязателен.",
  "validation.passwords-dont-match": "Пароли не совпадают.",
  "validation.confirm-password-required": "Подтверждение пароля обязательно.",

  "Forgot Password": "Забыли пароль",
  "Enter your email to reset your password": "Введите свою почту, чтобы сбросить пароль",
  "Enter your email": "Введите вашу почту",
  "Reset Password": "Сбросить пароль",
  "Back to Login": "← Назад ко входу",

  "Control Devices": "Управление устройствами",
  "Light": "Свет",
  "Thermostat": "Термостат",
  "Fan": "Вентилятор",
  "Home": "Главная",
  "Notifications": "Уведомления",
  "Profile": "Профиль",
"Change Language":"Сменить язык",
  "✏️  Edit Username": "✏️  Редактировать имя пользователя",
  "🌍  Language": "🌍  Язык",
  "🚪 Logout": "🚪  Выйти",
  "Are you sure you want to logout?": "Вы уверены, что хотите выйти?",
  "Logout successful": "Выход выполнен успешно",
  "No": "Нет",
  "Yes": "Да",
  "Confirm Logout": "Подтвердить выход",
  "👋 Hello": "Привет",
  "Edit Your Username": "Изменить имя пользователя",
  "Save": "Сохранить",
  "Name updated successfully!": "Имя успешно обновлено!",
  "Failed to update name. Try again.": "Не удалось обновить имя. Попробуйте снова.",
  "Your Username":"Ваше имя пользователя",
  "Confirm":"Подтвердить"
}
